g42cloudsdksmn/__init__.py
g42cloudsdksmn/v2/__init__.py
g42cloudsdksmn/v2/smn_async_client.py
g42cloudsdksmn/v2/smn_client.py
g42cloudsdksmn/v2/model/__init__.py
g42cloudsdksmn/v2/model/access_policy.py
g42cloudsdksmn/v2/model/add_subscription_request.py
g42cloudsdksmn/v2/model/add_subscription_request_body.py
g42cloudsdksmn/v2/model/add_subscription_response.py
g42cloudsdksmn/v2/model/application_endpoint.py
g42cloudsdksmn/v2/model/application_item.py
g42cloudsdksmn/v2/model/batch_create_or_delete_resource_tags_request.py
g42cloudsdksmn/v2/model/batch_create_or_delete_resource_tags_request_body.py
g42cloudsdksmn/v2/model/batch_create_or_delete_resource_tags_response.py
g42cloudsdksmn/v2/model/cancel_subscription_request.py
g42cloudsdksmn/v2/model/cancel_subscription_response.py
g42cloudsdksmn/v2/model/create_application_endpoint_request.py
g42cloudsdksmn/v2/model/create_application_endpoint_request_body.py
g42cloudsdksmn/v2/model/create_application_endpoint_response.py
g42cloudsdksmn/v2/model/create_application_request.py
g42cloudsdksmn/v2/model/create_application_request_body.py
g42cloudsdksmn/v2/model/create_application_response.py
g42cloudsdksmn/v2/model/create_logtank_request.py
g42cloudsdksmn/v2/model/create_logtank_request_body.py
g42cloudsdksmn/v2/model/create_logtank_response.py
g42cloudsdksmn/v2/model/create_message_template_request.py
g42cloudsdksmn/v2/model/create_message_template_request_body.py
g42cloudsdksmn/v2/model/create_message_template_response.py
g42cloudsdksmn/v2/model/create_resource_tag_request.py
g42cloudsdksmn/v2/model/create_resource_tag_request_body.py
g42cloudsdksmn/v2/model/create_resource_tag_response.py
g42cloudsdksmn/v2/model/create_topic_request.py
g42cloudsdksmn/v2/model/create_topic_request_body.py
g42cloudsdksmn/v2/model/create_topic_response.py
g42cloudsdksmn/v2/model/delete_application_endpoint_request.py
g42cloudsdksmn/v2/model/delete_application_endpoint_response.py
g42cloudsdksmn/v2/model/delete_application_request.py
g42cloudsdksmn-0.0.10b0.dist-info/LICENSE
g42cloudsdksmn-0.0.10b0.dist-info/METADATA
g42cloudsdksmn-0.0.10b0.dist-info/WHEEL
g42cloudsdksmn-0.0.10b0.dist-info/top_level.txt
g42cloudsdksmn-0.0.10b0.dist-info/RECORD
